orange3_tableau_hyper-0.0.1.dist-info/licenses/LICENSE
orangecontrib/__init__.py
orangecontrib/hyper/__init__.py
orangecontrib/hyper/misc/__init__.py
orangecontrib/hyper/misc/hyper.py
orange3_tableau_hyper-0.0.1.dist-info/METADATA
orange3_tableau_hyper-0.0.1.dist-info/WHEEL
orange3_tableau_hyper-0.0.1.dist-info/entry_points.txt
orange3_tableau_hyper-0.0.1.dist-info/top_level.txt
orange3_tableau_hyper-0.0.1.dist-info/RECORD
